cyberuskey/__init__.py
cyberuskey/cyberuskey.py
cyberuskey/exceptions.py
cyberuskey/utils.py
cyberuskey-0.0.1.dist-info/LICENSE
cyberuskey-0.0.1.dist-info/METADATA
cyberuskey-0.0.1.dist-info/WHEEL
cyberuskey-0.0.1.dist-info/top_level.txt
cyberuskey-0.0.1.dist-info/RECORD
