Metadata-Version: 2.1
Name: cyberuskey
Version: 0.0.1
Summary: Cyberus Key authenticate library
Home-page: https://github.com/CyberusLabs/cyberuskey-python
Author: CyberusLabs sp.z.o.o.
Author-email: support@cyberuslabs.com
License: UNKNOWN
Platform: UNKNOWN
Classifier: Programming Language :: Python :: 3
Classifier: License :: OSI Approved :: MIT License
Classifier: Operating System :: OS Independent
Requires-Python: >=3.6
Requires-Dist: requests (>=2.23.0)
Requires-Dist: PyJWT (>=1.7.1)
Requires-Dist: cryptography (>=2.9.2)
